MANIFEST.in
README
README.md
dobackup.py
gmailbackup.py
sample.ini
setup.py
EncryptedGmailBackup.egg-info/PKG-INFO
EncryptedGmailBackup.egg-info/SOURCES.txt
EncryptedGmailBackup.egg-info/dependency_links.txt
EncryptedGmailBackup.egg-info/entry_points.txt
EncryptedGmailBackup.egg-info/requires.txt
EncryptedGmailBackup.egg-info/top_level.txt