Metadata-Version: 1.1
Name: EncryptedGmailBackup
Version: 0.0.4beta2
Summary: Backup your GMail account with GPG encryption.
Home-page: https://github.com/sholiday/encrypted-gmail-backup
Author: Stephen Holiday
Author-email: stephen.holiday@gmail.com
License: UNKNOWN
Platform: UNKNOWN
Classifier: Development Status :: 3 - Alpha
Classifier: Environment :: Console
Classifier: Intended Audience :: Developers
Classifier: Intended Audience :: End Users/Desktop
Classifier: License :: OSI Approved :: Apache Software License
Classifier: Operating System :: MacOS :: MacOS X
Classifier: Operating System :: POSIX
Classifier: Operating System :: Unix
Classifier: Programming Language :: Python :: 2.7
Classifier: Programming Language :: Python
Requires: gnupg
Requires: psutil
